odoo/addons/l10n_th_bank_payment_export/README.rst
odoo/addons/l10n_th_bank_payment_export/__init__.py
odoo/addons/l10n_th_bank_payment_export/__manifest__.py
odoo/addons/l10n_th_bank_payment_export/data/bank_payment_export_sequence.xml
odoo/addons/l10n_th_bank_payment_export/data/report_action.xml
odoo/addons/l10n_th_bank_payment_export/data/server_action.xml
odoo/addons/l10n_th_bank_payment_export/i18n/l10n_th_bank_payment_export.pot
odoo/addons/l10n_th_bank_payment_export/models/__init__.py
odoo/addons/l10n_th_bank_payment_export/models/account_payment.py
odoo/addons/l10n_th_bank_payment_export/models/bank_payment_export.py
odoo/addons/l10n_th_bank_payment_export/models/bank_payment_export_line.py
odoo/addons/l10n_th_bank_payment_export/models/bank_payment_template.py
odoo/addons/l10n_th_bank_payment_export/models/res_partner.py
odoo/addons/l10n_th_bank_payment_export/models/res_partner_bank.py
odoo/addons/l10n_th_bank_payment_export/readme/CONFIGURE.rst
odoo/addons/l10n_th_bank_payment_export/readme/CONTRIBUTORS.rst
odoo/addons/l10n_th_bank_payment_export/readme/DESCRIPTION.rst
odoo/addons/l10n_th_bank_payment_export/readme/USAGE.rst
odoo/addons/l10n_th_bank_payment_export/security/bank_payment_export_security.xml
odoo/addons/l10n_th_bank_payment_export/security/ir.model.access.csv
odoo/addons/l10n_th_bank_payment_export/static/description/icon.png
odoo/addons/l10n_th_bank_payment_export/static/description/index.html
odoo/addons/l10n_th_bank_payment_export/templates/__init__.py
odoo/addons/l10n_th_bank_payment_export/templates/report_bank_payment_export_xlsx.py
odoo/addons/l10n_th_bank_payment_export/templates/report_template.xml
odoo/addons/l10n_th_bank_payment_export/tests/__init__.py
odoo/addons/l10n_th_bank_payment_export/tests/bank_payment_export_tester.py
odoo/addons/l10n_th_bank_payment_export/tests/common.py
odoo/addons/l10n_th_bank_payment_export/tests/test_bank_payment_export.py
odoo/addons/l10n_th_bank_payment_export/views/account_payment_view.xml
odoo_addon_l10n_th_bank_payment_export-16.0.1.0.0.4.dist-info/METADATA
odoo_addon_l10n_th_bank_payment_export-16.0.1.0.0.4.dist-info/WHEEL
odoo_addon_l10n_th_bank_payment_export-16.0.1.0.0.4.dist-info/top_level.txt
odoo_addon_l10n_th_bank_payment_export-16.0.1.0.0.4.dist-info/RECORD
