Metadata-Version: 2.1
Name: odoo-addon-l10n_th_bank_payment_export
Version: 16.0.1.0.0.4
Summary: Base export payment text file to bank
Home-page: https://github.com/OCA/l10n-thailand
Author: Ecosoft, Odoo Community Association (OCA)
Author-email: support@odoo-community.org
License: AGPL-3
Classifier: Programming Language :: Python
Classifier: Framework :: Odoo
Classifier: Framework :: Odoo :: 16.0
Classifier: License :: OSI Approved :: GNU Affero General Public License v3
Classifier: Development Status :: 3 - Alpha
Requires-Python: >=3.10
Requires-Dist: odoo-addon-partner-bank-code <16.1dev,>=16.0dev
Requires-Dist: odoo-addon-report-xlsx-helper <16.1dev,>=16.0dev
Requires-Dist: odoo <16.1dev,>=16.0a
